gtars/__init__.py
gtars/__init__.pyi
gtars/genomic_distributions/__init__.py
gtars/genomic_distributions/__init__.pyi
gtars/gtars.cpython-38-x86_64-linux-gnu.so
gtars/models/__init__.py
gtars/models/__init__.pyi
gtars/refget/__init__.py
gtars/refget/__init__.pyi
gtars/tokenizers/__init__.py
gtars/tokenizers/__init__.pyi
gtars/utils/__init__.py
gtars/utils/__init__.pyi
gtars-0.6.0.dist-info/METADATA
gtars-0.6.0.dist-info/WHEEL
gtars-0.6.0.dist-info/RECORD
