Metadata-Version: 2.4
Name: gtars
Version: 0.6.0
Classifier: Programming Language :: Rust
Classifier: Programming Language :: Python :: Implementation :: CPython
Classifier: Programming Language :: Python :: Implementation :: PyPy
Requires-Dist: pytest>=8.3.4
Requires-Dist: pytest-cov>=6.0.0
Requires-Dist: maturin>=1.8.1
Requires-Python: >=3.8
